MANIFEST.in
README.md
setup.cfg
setup.py
utf8forgood/__init__.py
utf8forgood.egg-info/PKG-INFO
utf8forgood.egg-info/SOURCES.txt
utf8forgood.egg-info/dependency_links.txt
utf8forgood.egg-info/not-zip-safe
utf8forgood.egg-info/top_level.txt