Metadata-Version: 1.0
Name: utf8forgood
Version: 0.1.3
Summary: "Simple is better than complex", Tim Peters, The Zen Of Python
Home-page: UNKNOWN
Author: miraculixx
Author-email: miraculixx at github
License: BSD
Platform: UNKNOWN
